synthlang/__init__.py
synthlang/cli.py
synthlang/config.py
synthlang/core/__init__.py
synthlang/core/base.py
synthlang/core/classifier.py
synthlang/core/evolver.py
synthlang/core/finetune.py
synthlang/core/generator.py
synthlang/core/optimizer.py
synthlang/core/prompt_manager.py
synthlang/core/signatures.py
synthlang/core/translator.py
synthlang/core/types.py
synthlang/prompt_evolution_20250111_060348.json
synthlang/prompt_evolution_20250111_060431.json
synthlang/prompt_evolution_20250111_060450.json
synthlang/prompt_evolution_20250111_060540.json
synthlang/prompt_evolution_20250111_060604.json
synthlang/test_program.json
synthlang/utils/__init__.py
synthlang/utils/env.py
synthlang/utils/logger.py
synthlang-0.1.4.dist-info/METADATA
synthlang-0.1.4.dist-info/WHEEL
synthlang-0.1.4.dist-info/entry_points.txt
synthlang-0.1.4.dist-info/RECORD
